sentry_nodestore_mongodb/__init__.py
sentry_nodestore_mongodb/backend.py
sentry_nodestore_mongodb-0.1.0.dist-info/METADATA
sentry_nodestore_mongodb-0.1.0.dist-info/WHEEL
sentry_nodestore_mongodb-0.1.0.dist-info/top_level.txt
sentry_nodestore_mongodb-0.1.0.dist-info/RECORD
