Metadata-Version: 2.4
Name: sentry-nodestore-mongodb
Version: 0.1.0
Summary: Sentry nodestore MongoDB backend
Home-page: https://github.com/xterm-inator/sentry-nodestore-mongodb
Author: David Smith
Author-email: david@xterm.me
License: Apache-2.0
Project-URL: Bug Tracker, https://github.com/xterm-inator/sentry-nodestore-mongodb/issues
Project-URL: CI, https://ggithub.com/xterm-inator/sentry-nodestore-mongodb/actions
Project-URL: Source Code, https://github.com/xterm-inator/sentry-nodestore-mongodb
Keywords: sentry,mongodb,nodestore,backend
Classifier: Development Status :: 3 - Alpha
Classifier: Intended Audience :: Developers
Classifier: Operating System :: POSIX
Classifier: Operating System :: MacOS :: MacOS X
Classifier: Operating System :: Microsoft :: Windows
Classifier: Programming Language :: Python
Classifier: Operating System :: OS Independent
Requires-Dist: sentry==25.*
Requires-Dist: pymongo==4.*
Dynamic: author
Dynamic: author-email
Dynamic: classifier
Dynamic: description
Dynamic: description-content-type
Dynamic: home-page
Dynamic: keywords
Dynamic: license
Dynamic: project-url
Dynamic: requires-dist
Dynamic: summary
